gddownloader/__init__.py
gddownloader/example.csv
gddownloader/__tests__/__init__.py
gddownloader/core/__init__.py
gddownloader/core/cli.py
gddownloader/core/downloader.py
GdDownloader-0.0.1.dist-info/LICENSE
GdDownloader-0.0.1.dist-info/METADATA
GdDownloader-0.0.1.dist-info/WHEEL
GdDownloader-0.0.1.dist-info/top_level.txt
GdDownloader-0.0.1.dist-info/RECORD
