Metadata-Version: 2.1
Name: GdDownloader
Version: 0.0.1
Summary: easy wrapper for downloading google drive files using only shareable link
Home-page: https://github.com/deven96/drive_downloader
Author: Domnan Diretnan, Mmadu Manasseh
Author-email: diretnandomnan@gmail.com
License: MIT
Platform: UNKNOWN
Classifier: Programming Language :: Python :: 3
Classifier: License :: OSI Approved :: MIT License
Classifier: Operating System :: OS Independent
Requires-Dist: progressbar
Requires-Dist: urllib3
Requires-Dist: pandas
